hlpl_composer/__init__.py
hlpl_composer/__main__.py
hlpl_composer/hlpl_arabic_words_synonym_antonym.db
hlpl_composer/hlpl_arabic_words_templates.db
hlpl_composer/hlpl_composer.py
hlpl_composer/hlpl_composer_settings.db
hlpl_composer/hlpl_conjugate.py
hlpl_composer/hlpl_functions.py
hlpl_composer/hlpl_license_about.py
hlpl_composer/setup.cfg
hlpl_composer/images/__init__.py
hlpl_composer/images/about.png
hlpl_composer/images/act++.png
hlpl_composer/images/act81.png
hlpl_composer/images/act811.png
hlpl_composer/images/act82 - Copy.png
hlpl_composer/images/act82.png
hlpl_composer/images/act822.png
hlpl_composer/images/arrow-continue.png
hlpl_composer/images/arrow-curve-180-left.png
hlpl_composer/images/arrow-curve.png
hlpl_composer/images/blue-folder-open-document.png
hlpl_composer/images/bold.png
hlpl_composer/images/clipboard-paste-document-text.png
hlpl_composer/images/composer 32.png
hlpl_composer/images/composer.png
hlpl_composer/images/copy.png
hlpl_composer/images/create.png
hlpl_composer/images/curve.png
hlpl_composer/images/cut.png
hlpl_composer/images/disk--pencil.png
hlpl_composer/images/disk.png
hlpl_composer/images/document-copy.png
hlpl_composer/images/edit-alignment-center.png
hlpl_composer/images/edit-alignment-justify.png
hlpl_composer/images/edit-alignment-right.png
hlpl_composer/images/edit-alignment.png
hlpl_composer/images/edit-bold.png
hlpl_composer/images/edit-color.png
hlpl_composer/images/edit-italic.png
hlpl_composer/images/edit-list-order.png
hlpl_composer/images/edit-list.png
hlpl_composer/images/edit-underline.png
hlpl_composer/images/edit_redo.png
hlpl_composer/images/edit_undo.png
hlpl_composer/images/ex.png
hlpl_composer/images/exit.png
hlpl_composer/images/font.png
hlpl_composer/images/forum2.png
hlpl_composer/images/g1.png
hlpl_composer/images/g11.jpg
hlpl_composer/images/g11.png
hlpl_composer/images/girl.png
hlpl_composer/images/girl2.png
hlpl_composer/images/guide.png
hlpl_composer/images/guide2.png
hlpl_composer/images/hlpl.png
hlpl_composer-1.1.0.dist-info/LICENSE
hlpl_composer-1.1.0.dist-info/METADATA
hlpl_composer-1.1.0.dist-info/WHEEL
hlpl_composer-1.1.0.dist-info/entry_points.txt
hlpl_composer-1.1.0.dist-info/top_level.txt
hlpl_composer-1.1.0.dist-info/RECORD
