Metadata-Version: 2.1
Name: hlpl-composer
Version: 1.1.0
Summary: Text composer and analyser
Home-page: https://composer.hlpl.net
Download-URL: https://composer.hlpl.net/download/
Author: Ahmida Bendjoudi
Author-email: email@hlpl.net
License: MIT
Project-URL: hlpl, https://hlpl.net
Project-URL: hlpl_composer-docs, https://docs.hlpl.net
Project-URL: hlpl_composer-forum, https://hlpl.net/forums/hlpl-composer
Project-URL: hlpl_composer-resource, https://hlpl.net/resources
Project-URL: hlpl_composer-github, https://github.com/hlpl/composer
Keywords: hlpl_composer,hlpl composer,hlpl-composer,text composer,text analyser,hlpl
Platform: UNKNOWN
Classifier: Framework :: Robot Framework
Classifier: Framework :: Robot Framework :: Library
Classifier: Framework :: Robot Framework :: Tool
Classifier: Natural Language :: Arabic
Classifier: Natural Language :: English
Requires-Python: >=3, <3.9
License-File: LICENSE
